{"TextNeeded": null, "SourceNotes": null, "Transcription": "Completed", "PlaceNotes": null, "Source": null, "Latitude": "42.465", "NoKnownText": null, "Circa": null, "Province": "Tarragona", "RegnalEnd": "1263", "Fragment": null, "GeneralNotes": null, "ClassificationNotes": null, "TranscriptionNotes": null, "Delegated": null, "Day": "22", "DatingNotes": null, "BiblioRefs": null, "Language": "Old Spanish", "LanguageNotes": null, "CountryModern": "Spain", "SourceOther": null, "OCR": "Yes", "Longitude": "-2.445556", "Place": "Logro\u00f1o", "IssuingAuthorityAlt": null, "EditionOther": null, "Classification": "Diocesan", "Diocese": "Calahorra y La Calzada", "RecordID": "640", "Month": "4", "Edition": "Synodicon Hispanum, VIII, pp10-18", "BaseText": ["Library Scan", "Hard Copy Scan"], "IssuingAuthority": "Aznar L\u00f3pez de Cadreita", "Year": "1240", "RegnalStart": "1238"}