{"TextNeeded": null, "SourceNotes": null, "Transcription": "Completed", "PlaceNotes": null, "Source": null, "Latitude": "43.85", "NoKnownText": null, "Circa": null, "Province": "[Holy See]", "RegnalEnd": null, "Fragment": null, "GeneralNotes": null, "ClassificationNotes": null, "TranscriptionNotes": null, "Delegated": null, "Day": null, "DatingNotes": null, "BiblioRefs": null, "Language": "Latin", "LanguageNotes": null, "CountryModern": "Italy", "SourceOther": null, "OCR": "Yes", "Longitude": "10.5", "Place": "Lucca", "IssuingAuthorityAlt": "Guerrigo", "EditionOther": "Mansi 23, coll 821-24", "Classification": "Diocesan", "Diocese": "Lucca", "RecordID": "1617", "Month": null, "Edition": "Dinelli, Dei sinodi della diocesi di Lucca, 53-58", "BaseText": "WebDownload", "IssuingAuthority": "Guercio Tebalducci", "Year": "1253", "RegnalStart": null}