{"TextNeeded": null, "SourceNotes": null, "Transcription": "Completed", "PlaceNotes": null, "Source": null, "Latitude": "39.470239", "NoKnownText": null, "Circa": null, "Province": "Tarragona", "RegnalEnd": "1396", "Fragment": null, "GeneralNotes": null, "ClassificationNotes": "Canons complain that bishop convoked a synod without their approval", "TranscriptionNotes": null, "Delegated": null, "Day": "24", "DatingNotes": null, "BiblioRefs": null, "Language": "Latin", "LanguageNotes": null, "CountryModern": "Spain", "SourceOther": null, "OCR": "Yes", "Longitude": "-0.376805", "Place": "Valencia", "IssuingAuthorityAlt": "Jaime de Arag\u00f3n", "EditionOther": "Perez de Heredia, Sinodos, 773-776", "Classification": "Other", "Diocese": "Valencia", "RecordID": "421", "Month": "1", "Edition": "Synodicon Hispanum, XII, 801-802", "BaseText": ["Library Scan", "Hard Copy Scan"], "IssuingAuthority": "Jaume de Prades i de Foix", "Year": "1370", "RegnalStart": "1369"}