{"TextNeeded": null, "SourceNotes": null, "Transcription": "Reviewed ", "PlaceNotes": null, "Source": null, "Latitude": "53.075833", "NoKnownText": null, "Circa": null, "Province": "Bremen", "RegnalEnd": null, "Fragment": null, "GeneralNotes": null, "ClassificationNotes": null, "TranscriptionNotes": null, "Delegated": null, "Day": null, "DatingNotes": null, "BiblioRefs": "Mentioned in Pixton, Watchmen, 442", "Language": "Latin", "LanguageNotes": null, "CountryModern": "Germany", "SourceOther": null, "OCR": null, "Longitude": "8.8075", "Place": "Bremen", "IssuingAuthorityAlt": null, "EditionOther": null, "Classification": "Legatine", "Diocese": "Bremen", "RecordID": "2006", "Month": "11", "Edition": "Mansi 23, coll 1155-62", "BaseText": "Data Capture", "IssuingAuthority": "Guido di S. Lorenzo in Lucina", "Year": "1266", "RegnalStart": null}