{"TextNeeded": null, "SourceNotes": "https://books.google.com/books?id=FRtUAAAAcAAJ", "Transcription": "Reviewed ", "PlaceNotes": null, "Source": null, "Latitude": "51.02", "NoKnownText": null, "Circa": null, "Province": "Canterbury", "RegnalEnd": "1333", "Fragment": null, "GeneralNotes": null, "ClassificationNotes": null, "TranscriptionNotes": null, "Delegated": null, "Day": null, "DatingNotes": null, "BiblioRefs": null, "Language": "Latin", "LanguageNotes": null, "CountryModern": "England", "SourceOther": null, "OCR": null, "Longitude": "0.26", "Place": "Mayfield", "IssuingAuthorityAlt": "Simon Meopham", "EditionOther": "Mansi 25, col 976-980", "Classification": "Provincial", "Diocese": null, "RecordID": "348", "Month": null, "Edition": "Wilkins II, 560-561", "BaseText": ["GoogleBooks", "Data Capture"], "IssuingAuthority": "Simon Mepeham", "Year": "1332", "RegnalStart": "1328"}